equation_scraper/__init__.py
equation_scraper/functions/load.py
equation_scraper/functions/parse.py
equation_scraper/functions/plot.py
equation_scraper/functions/scrape.py
equation_scraper/functions/scrape_and_parse.py
equation_scraper-1.0.0.dist-info/METADATA
equation_scraper-1.0.0.dist-info/WHEEL
equation_scraper-1.0.0.dist-info/licenses/LICENSE.md
equation_scraper-1.0.0.dist-info/RECORD
