Metadata-Version: 2.1
Name: equation-scraper
Version: 1.0.0
Summary: This package scrapes Wikipedia for equations, parses the equations, and builds priors of operations and functions.
Project-URL: Homepage, https://musslick.github.io/AER_website/Research.html
Project-URL: Repository, https://github.com/AutoResearch/equation-scraper
Project-URL: Documentation, https://autoresearch.github.io/equation-scraper/
Author-email: Chad Williams <chad_williams@brown.edu>
License-File: LICENSE.md
Requires-Python: >=3.7
Requires-Dist: antlr4-python3-runtime==4.10
Requires-Dist: beautifulsoup4~=4.11.2
Requires-Dist: equation-tree~=0.0.25
Requires-Dist: matplotlib~=3.6.3
Requires-Dist: numpy~=1.24.2
Requires-Dist: requests~=2.28.2
Requires-Dist: sympy~=1.11.1
Requires-Dist: tqdm~=4.65.0
